pyficache/__init__.py
pyficache/line_numbers.py
pyficache/main.py
pyficache/pyasm.py
pyficache/version.py
pyficache-2.5.0.dist-info/licenses/COPYING
pyficache-2.5.0.dist-info/METADATA
pyficache-2.5.0.dist-info/WHEEL
pyficache-2.5.0.dist-info/top_level.txt
pyficache-2.5.0.dist-info/RECORD
