Metadata-Version: 2.4
Name: pyficache
Version: 2.5.0
Summary: Cache and colorize lines and file information which are generally Python program or Python Bytecode
Author-email: Rocky Bernstein <rocky@gnu.org>
License-Expression: GPL-3.0-or-later
Project-URL: Homepage, https://pypi.org/project/pyficache/
Project-URL: Downloads, https://github.com/rocky/python-filecache/releases
Keywords: Python debugger,Python bytecode
Classifier: Development Status :: 5 - Production/Stable
Classifier: Environment :: Console
Classifier: Intended Audience :: Developers
Classifier: Operating System :: OS Independent
Classifier: Programming Language :: Python
Classifier: Topic :: Software Development :: Debuggers
Classifier: Topic :: Software Development :: Libraries :: Python Modules
Classifier: Programming Language :: Python :: 3.0
Classifier: Programming Language :: Python :: 3.1
Classifier: Programming Language :: Python :: 3.2
Classifier: Programming Language :: Python :: 3.3
Classifier: Programming Language :: Python :: 3.4
Classifier: Programming Language :: Python :: 3.5
Classifier: Programming Language :: Python :: 3.6
Classifier: Programming Language :: Python :: 3.7
Classifier: Programming Language :: Python :: 3.8
Classifier: Programming Language :: Python :: 3.9
Classifier: Programming Language :: Python :: 3.10
Classifier: Programming Language :: Python :: 3.11
Classifier: Programming Language :: Python :: 3.12
Classifier: Programming Language :: Python :: 3.13
Classifier: Programming Language :: Python :: Implementation :: PyPy
License-File: COPYING
Requires-Dist: xdis<6.2.0,>=6.0.0
Requires-Dist: term-background>=1.0.2
Provides-Extra: dev
Requires-Dist: flake8; extra == "dev"
Requires-Dist: pre-commit; extra == "dev"
Requires-Dist: pytest; extra == "dev"
Dynamic: license-file
